{
  "main": {
    "id": "bf1e734fec861b3a",
    "type": "split",
    "children": [
      {
        "id": "a5c2c69042f848ec",
        "type": "tabs",
        "children": [
          {
            "id": "0388da5f62d16551",
            "type": "leaf",
            "state": {
              "type": "markdown",
              "state": {
                "file": "Angol/Speaking/Notes/9. How children learn language.md",
                "mode": "source",
                "source": false
              },
              "icon": "lucide-file",
              "title": "9. How children learn language"
            }
          }
        ]
      }
    ],
    "direction": "vertical"
  },
  "left": {
    "id": "af1d6a7d26941b90",
    "type": "split",
    "children": [
      {
        "id": "3322cdc5e3f157fd",
        "type": "tabs",
        "children": [
          {
            "id": "2872af3a65a336f0",
            "type": "leaf",
            "state": {
              "type": "file-explorer",
              "state": {
                "sortOrder": "alphabetical",
                "autoReveal": false
              },
              "icon": "lucide-folder-closed",
              "title": "Files"
            }
          },
          {
            "id": "c586adfe478dc0eb",
            "type": "leaf",
            "state": {
              "type": "search",
              "state": {
                "query": "",
                "matchingCase": false,
                "explainSearch": false,
                "collapseAll": false,
                "extraContext": false,
                "sortOrder": "alphabetical"
              },
              "icon": "lucide-search",
              "title": "Search"
            }
          },
          {
            "id": "d4bb1b2b66dc2c86",
            "type": "leaf",
            "state": {
              "type": "bookmarks",
              "state": {},
              "icon": "lucide-bookmark",
              "title": "Bookmarks"
            }
          }
        ]
      }
    ],
    "direction": "horizontal",
    "width": 300
  },
  "right": {
    "id": "2cb82efc64c1ecb6",
    "type": "split",
    "children": [
      {
        "id": "f020085433131c94",
        "type": "tabs",
        "children": [
          {
            "id": "c10b1dfc0e83ad17",
            "type": "leaf",
            "state": {
              "type": "tag",
              "state": {
                "sortOrder": "frequency",
                "useHierarchy": true,
                "showSearch": false,
                "searchQuery": ""
              },
              "icon": "lucide-tags",
              "title": "Tags"
            }
          },
          {
            "id": "ff72da04d80cc988",
            "type": "leaf",
            "state": {
              "type": "outline",
              "state": {
                "file": "Angol/Speaking/Notes/9. How children learn language.md",
                "followCursor": false,
                "showSearch": false,
                "searchQuery": ""
              },
              "icon": "lucide-list",
              "title": "Outline of 9. How children learn language"
            }
          },
          {
            "id": "9d41fec148750ead",
            "type": "leaf",
            "state": {
              "type": "backlink",
              "state": {
                "file": "Történelem/Kiegyezés.md",
                "collapseAll": false,
                "extraContext": false,
                "sortOrder": "alphabetical",
                "showSearch": false,
                "searchQuery": "",
                "backlinkCollapsed": false,
                "unlinkedCollapsed": true
              },
              "icon": "links-coming-in",
              "title": "Backlinks for Kiegyezés"
            }
          },
          {
            "id": "139a0837b976fb5f",
            "type": "leaf",
            "state": {
              "type": "outgoing-link",
              "state": {
                "file": "Történelem/Kiegyezés.md",
                "linksCollapsed": false,
                "unlinkedCollapsed": true
              },
              "icon": "links-going-out",
              "title": "Outgoing links from Kiegyezés"
            }
          }
        ],
        "currentTab": 1
      },
      {
        "id": "0c810eb29c9863af",
        "type": "tabs",
        "children": [
          {
            "id": "5927e1f7f496c34b",
            "type": "leaf",
            "state": {
              "type": "git-view",
              "state": {},
              "icon": "git-pull-request",
              "title": "Source Control"
            }
          }
        ]
      }
    ],
    "direction": "horizontal",
    "width": 300
  },
  "left-ribbon": {
    "hiddenItems": {
      "switcher:Open quick switcher": false,
      "graph:Open graph view": false,
      "canvas:Create new canvas": false,
      "daily-notes:Open today's daily note": true,
      "templates:Insert template": true,
      "command-palette:Open command palette": false,
      "obsidian-git:Open Git source control": false
    }
  },
  "active": "0388da5f62d16551",
  "lastOpenFiles": [
    "Angol/Speaking/Texts/9. How children learn language.md",
    "Angol/Speaking/Notes/9. How children learn language.md",
    "Angol/Speaking/Texts/6. The reality of sci-fi.md",
    "Angol/Speaking/Notes/6. The reality of sci-fi.md",
    "Angol/Speaking/Notes/7. What's your personality.md",
    "Angol/Speaking/Texts/7. What's your personality.md",
    "Angol/Speaking/Texts/8. Childhood memories.md",
    "Angol/Speaking/Notes/8. Childhood memories.md",
    "Angol/Speaking/Notes/2. The best way to spot a liar.md",
    "Angol/Speaking/Notes/1. Classic student house arguments.md",
    "Angol/Speaking/Notes/5. What makes a city attractive.md",
    "Angol/Speaking/Texts/5. What makes a city attractive.md",
    "Angol/Speaking/Notes/4. 8 tips on how to spot fake news.md",
    "Angol/Speaking/Texts/4. 8 tips on how to spot fake news.md",
    "Angol/Speaking/Notes/3. A case of identity theft.md",
    "Angol/Speaking/Texts/1. Classic student house arguments.md",
    "Angol/Speaking/Texts/3. A case of identity theft.md",
    "Angol/Speaking/Texts/2. The best way to spot a liar.md",
    "Angol/Speaking/Notes",
    "Angol/Speaking/Texts",
    "Angol/Speaking",
    "Untitled",
    "Történelem/Kiegyezés.md",
    "Angol/Speaking - Texts",
    "Angol",
    "Untitled.canvas",
    "2025-05-26.md",
    "Biológia/Érzékelés/7. Látás.md",
    "Történelem",
    "Biológia/Érzékelés/6. Egyensúlyozó szerv.md",
    "Biológia/Érzékelés/5. Hallás.md",
    "Biológia/Érzékelés/4. Szaglás, ízlelés.md",
    "Biológia/Érzékelés/3. Limbikus rendszer.md",
    "Biológia/Érzékelés/2. Bőrérzékelés.md",
    "Biológia/Érzékelés/1. Érzékelés.md~",
    "Biológia/Érzékelés/2. Bőrérzékelés.md~",
    "Biológia/Érzékelés/4913",
    "Biológia/Érzékelés/img/egyensulyozas.jpeg",
    "Biológia/Érzékelés/img/hallas2.jpg",
    "Biológia/Érzékelés/img/hallas1.jpg",
    "Biológia/Érzékelés/img/szaglas.jpg",
    "Biológia/Érzékelés/img/izleles2.jpg",
    "Biológia/Érzékelés/img/izleles1.jpg",
    "Biológia/Érzékelés/img/bor1.jpg",
    "Biológia/Érzékelés/img/bor2.jpg",
    "Biológia/Érzékelés/img/szemgolyo.jpg"
  ]
}